LICENSE
README.md
setup.py
sanic_rest_framework.egg-info/PKG-INFO
sanic_rest_framework.egg-info/SOURCES.txt
sanic_rest_framework.egg-info/dependency_links.txt
sanic_rest_framework.egg-info/requires.txt
sanic_rest_framework.egg-info/top_level.txt
srf/__init__.py
srf/authentication.py
srf/constant.py
srf/converter.py
srf/exception_handlers.py
srf/exceptions.py
srf/export_import_view.py
srf/fields.py
srf/filters.py
srf/generics.py
srf/helpers.py
srf/mixins.py
srf/paginations.py
srf/permissions.py
srf/request.py
srf/response.py
srf/routes.py
srf/serializers.py
srf/status.py
srf/throttling.py
srf/utils.py
srf/validators.py
srf/views.py
srf/viewsets.py
srf/cache/__init__.py
srf/cache/core.py
srf/cache/backends/__init__.py
srf/cache/backends/base.py
srf/cache/backends/locmem.py
srf/openapi/__init__.py
srf/openapi/autodoc.py
srf/openapi/builders.py
srf/openapi/core.py
srf/openapi/openapi.py
srf/openapi/utils.py