Metadata-Version: 2.1
Name: sanic-rest-framework
Version: 1.2.3
Summary: DOC...
Home-page: https://github.com/Tioit-Wang/sanic-rest-framework
Author: Tioit-Wang
Author-email: me@tioit.cc
License: UNKNOWN
Download-URL: https://codeload.github.com/Tioit-Wang/sanic-rest-framework/zip/refs/heads/main
Platform: UNKNOWN
License-File: LICENSE
